bpal410/cdk_managed_ad/__init__.py
bpal410/cdk_managed_ad/py.typed
bpal410/cdk_managed_ad/_jsii/__init__.py
bpal410/cdk_managed_ad/_jsii/cdk-managed-ad@0.0.1.jsii.tgz
bpal410.cdk_managed_ad-0.0.1.dist-info/LICENSE
bpal410.cdk_managed_ad-0.0.1.dist-info/METADATA
bpal410.cdk_managed_ad-0.0.1.dist-info/WHEEL
bpal410.cdk_managed_ad-0.0.1.dist-info/top_level.txt
bpal410.cdk_managed_ad-0.0.1.dist-info/RECORD
