Metadata-Version: 2.1
Name: bpal410.cdk-managed-ad
Version: 0.0.1
Summary: AWS CDK constructs for Directory Service Managed AD
Home-page: https://github.com/bpal410/cdk-managed-ad.git
Author: bpal410<46696804+bpal410@users.noreply.github.com>
License: Apache-2.0
Project-URL: Source, https://github.com/bpal410/cdk-managed-ad.git
Classifier: Intended Audience :: Developers
Classifier: Operating System :: OS Independent
Classifier: Programming Language :: JavaScript
Classifier: Programming Language :: Python :: 3 :: Only
Classifier: Programming Language :: Python :: 3.8
Classifier: Programming Language :: Python :: 3.9
Classifier: Programming Language :: Python :: 3.10
Classifier: Programming Language :: Python :: 3.11
Classifier: Typing :: Typed
Classifier: Development Status :: 5 - Production/Stable
Classifier: License :: OSI Approved
Requires-Python: ~=3.8
License-File: LICENSE
Requires-Dist: aws-cdk-lib<3.0.0,>=2.173.2
Requires-Dist: constructs<11.0.0,>=10.0.5
Requires-Dist: jsii<2.0.0,>=1.106.0
Requires-Dist: publication>=0.0.3
Requires-Dist: typeguard<4.3.0,>=2.13.3
